pylemmy/__about__.py
pylemmy/__init__.py
pylemmy/endpoints.py
pylemmy/lemmy.py
pylemmy/py.typed
pylemmy/utils.py
pylemmy/api/__init__.py
pylemmy/api/auth.py
pylemmy/api/base.py
pylemmy/api/comment.py
pylemmy/api/community.py
pylemmy/api/listing.py
pylemmy/api/person.py
pylemmy/api/post.py
pylemmy/api/site.py
pylemmy/api/utils.py
pylemmy/models/__init__.py
pylemmy/models/comment.py
pylemmy/models/community.py
pylemmy/models/person.py
pylemmy/models/post.py
pylemmy-0.0.8.dist-info/METADATA
pylemmy-0.0.8.dist-info/WHEEL
pylemmy-0.0.8.dist-info/licenses/LICENSE.txt
pylemmy-0.0.8.dist-info/RECORD
