Metadata-Version: 2.1
Name: pylemmy
Version: 0.0.8
Summary: pylemmy enables simple access to Lemmy's API with Python
Project-URL: Documentation, https://dcferreira.com/pylemmy
Project-URL: Issues, https://github.com/dcferreira/pylemmy/issues
Project-URL: Source, https://github.com/dcferreira/pylemmy
Author-email: Daniel Ferreira <daniel.ferreira.1@gmail.com>
License-Expression: MIT
License-File: LICENSE.txt
Classifier: Development Status :: 4 - Beta
Classifier: Programming Language :: Python
Classifier: Programming Language :: Python :: 3.7
Classifier: Programming Language :: Python :: 3.8
Classifier: Programming Language :: Python :: 3.9
Classifier: Programming Language :: Python :: 3.10
Classifier: Programming Language :: Python :: 3.11
Classifier: Programming Language :: Python :: Implementation :: CPython
Classifier: Programming Language :: Python :: Implementation :: PyPy
Requires-Python: >=3.7
Requires-Dist: aiostream~=0.4.5
Requires-Dist: loguru>=0.3
Requires-Dist: pydantic<2.0,>=1.8
Requires-Dist: requests>=2.18
